pybook/__init__.py
pybook/view.py
pybook-1.dist-info/METADATA
pybook-1.dist-info/WHEEL
pybook-1.dist-info/entry_points.txt
pybook-1.dist-info/RECORD
